signal_ICT_Mohil_Koriya_92400133194/__init__.py
signal_ICT_Mohil_Koriya_92400133194/operations.py
signal_ICT_Mohil_Koriya_92400133194/trigonometric_signals.py
signal_ICT_Mohil_Koriya_92400133194/unitary_signals.py
signal_ict_mohil_koriya_92400133194-0.1.dist-info/METADATA
signal_ict_mohil_koriya_92400133194-0.1.dist-info/WHEEL
signal_ict_mohil_koriya_92400133194-0.1.dist-info/top_level.txt
signal_ict_mohil_koriya_92400133194-0.1.dist-info/RECORD
