Metadata-Version: 2.4
Name: signal_ICT_Mohil_koriya_92400133194
Version: 0.1
Summary: Python package for signal generation and operations
Author: Mohil Koriya
Requires-Dist: numpy
Requires-Dist: matplotlib
Dynamic: author
Dynamic: requires-dist
Dynamic: summary
